atedu/__init__.py
atedu/enums.py
atedu/gencode.py
atedu/setting.py
atedu/api/__init__.py
atedu/api/bpfactor/__init__.py
atedu/api/bpfactor/_factors.cp312-win_amd64.pyd
atedu/api/bpfactor/convertor.cp312-win_amd64.pyd
atedu/api/fundamental/__init__.py
atedu/api/fundamental/convertor.cp312-win_amd64.pyd
atedu/api/fundamental/company/__init__.py
atedu/api/fundamental/company/equity.cp312-win_amd64.pyd
atedu/api/fundamental/company/fid.cp312-win_amd64.pyd
atedu/api/fundamental/company/info.cp312-win_amd64.pyd
atedu/api/fundamental/company/ipo.cp312-win_amd64.pyd
atedu/api/fundamental/company/matters.cp312-win_amd64.pyd
atedu/api/fundamental/company/personnel.cp312-win_amd64.pyd
atedu/api/fundamental/company/restricted.cp312-win_amd64.pyd
atedu/api/fundamental/fdmt/__init__.py
atedu/api/fundamental/fdmt/bs.cp312-win_amd64.pyd
atedu/api/fundamental/fdmt/cf.cp312-win_amd64.pyd
atedu/api/fundamental/fdmt/expectation.cp312-win_amd64.pyd
atedu/api/fundamental/fdmt/indicator.cp312-win_amd64.pyd
atedu/api/fundamental/fdmt/ins.cp312-win_amd64.pyd
atedu/api/fundamental/fdmt/note.cp312-win_amd64.pyd
atedu/api/fundamental/mkt/__init__.py
atedu/api/fundamental/mkt/mkt.cp312-win_amd64.pyd
atedu/api/history/__init__.py
atedu/api/history/_history.cp312-win_amd64.pyd
atedu/api/history/convertor.cp312-win_amd64.pyd
atedu/api/orders/__init__.py
atedu/api/regfuncs/__init__.py
atedu/api/regfuncs/_regfuncs.cp312-win_amd64.pyd
atedu/api/regfuncs/convertor.cp312-win_amd64.pyd
atedu/api/riskmodel/__init__.py
atedu/api/riskmodel/convertor.cp312-win_amd64.pyd
atedu/api/riskmodel/rm.cp312-win_amd64.pyd
atedu/backtest/__init__.py
atedu/backtest/apiimpl.cp312-win_amd64.pyd
atedu/backtest/convertor.cp312-win_amd64.pyd
atedu/backtest/domain.cp312-win_amd64.pyd
atedu/backtest/main.cp312-win_amd64.pyd
atedu/backtest/syscls.cp312-win_amd64.pyd
atedu/backtest/model/__init__.py
atedu/backtest/model/accounts.cp312-win_amd64.pyd
atedu/backtest/model/orders.cp312-win_amd64.pyd
atedu-4.2.0.0.dist-info/LICENSE
atedu-4.2.0.0.dist-info/METADATA
atedu-4.2.0.0.dist-info/WHEEL
atedu-4.2.0.0.dist-info/top_level.txt
atedu-4.2.0.0.dist-info/RECORD
